.gitignore
MANIFEST.in
README.rst
setup.cfg
setup.py
docs/HISTORY.txt
docs/INSTALL.txt
docs/LICENSE.GPL
docs/LICENSE.txt
raptus/__init__.py
raptus.header.egg-info/PKG-INFO
raptus.header.egg-info/SOURCES.txt
raptus.header.egg-info/dependency_links.txt
raptus.header.egg-info/entry_points.txt
raptus.header.egg-info/namespace_packages.txt
raptus.header.egg-info/not-zip-safe
raptus.header.egg-info/requires.txt
raptus.header.egg-info/top_level.txt
raptus/header/README.txt
raptus/header/__init__.py
raptus/header/config.py
raptus/header/configure.zcml
raptus/header/interfaces.py
raptus/header/permission.zcml
raptus/header/setuphandlers.py
raptus/header/browser/__init__.py
raptus/header/browser/configure.zcml
raptus/header/browser/header.pt
raptus/header/browser/header_icon.gif
raptus/header/browser/info.pt
raptus/header/browser/viewlets.py
raptus/header/content/__init__.py
raptus/header/content/configure.zcml
raptus/header/content/header.py
raptus/header/i18n/raptus.header-de.mo
raptus/header/i18n/raptus.header-de.po
raptus/header/i18n/raptus.header-en.mo
raptus/header/i18n/raptus.header-en.po
raptus/header/i18n/raptus.header-fr.mo
raptus/header/i18n/raptus.header-fr.po
raptus/header/i18n/raptus.header.pot
raptus/header/profiles/default/cssregistry.xml
raptus/header/profiles/default/factorytool.xml
raptus/header/profiles/default/metadata.xml
raptus/header/profiles/default/propertiestool.xml
raptus/header/profiles/default/raptus.header_setupProperties.txt
raptus/header/profiles/default/rolemap.xml
raptus/header/profiles/default/skins.xml
raptus/header/profiles/default/types.xml
raptus/header/profiles/default/types/Header.xml
raptus/header/skins/raptus_header/raptus.header.css.dtml
raptus/header/tests/__init__.py
raptus/header/tests/base.py
raptus/header/tests/test_doctest.py