Metadata-Version: 1.1
Name: raptus.header
Version: 2.0b11
Summary: Provides a new folderish content type which may contain multiple images which are then displayed by the provided viewlet.
Home-page: https://github.com/Raptus/raptus.header
Author: Raptus AG
Author-email: dev@raptus.com
License: GPL
Platform: UNKNOWN
Classifier: Framework :: Plone
Classifier: Intended Audience :: Developers
Classifier: License :: OSI Approved :: GNU General Public License (GPL)
